jupyterlab_ariakedark_theme/__init__.py
jupyterlab_ariakedark_theme/_version.py
jupyterlab_ariakedark_theme-0.2.3.data/data/share/jupyter/labextensions/jupyterlab_ariakedark_theme/build_log.json
jupyterlab_ariakedark_theme-0.2.3.data/data/share/jupyter/labextensions/jupyterlab_ariakedark_theme/package.json
jupyterlab_ariakedark_theme-0.2.3.data/data/share/jupyter/labextensions/jupyterlab_ariakedark_theme/static/lib_index_js.4a091cac67d974fc2b5a.js
jupyterlab_ariakedark_theme-0.2.3.data/data/share/jupyter/labextensions/jupyterlab_ariakedark_theme/static/lib_index_js.4a091cac67d974fc2b5a.js.map
jupyterlab_ariakedark_theme-0.2.3.data/data/share/jupyter/labextensions/jupyterlab_ariakedark_theme/static/remoteEntry.cf778285bb8fdc6ae55f.js
jupyterlab_ariakedark_theme-0.2.3.data/data/share/jupyter/labextensions/jupyterlab_ariakedark_theme/static/remoteEntry.cf778285bb8fdc6ae55f.js.map
jupyterlab_ariakedark_theme-0.2.3.data/data/share/jupyter/labextensions/jupyterlab_ariakedark_theme/static/style.js
jupyterlab_ariakedark_theme-0.2.3.data/data/share/jupyter/labextensions/jupyterlab_ariakedark_theme/themes/jupyterlab_ariakedark_theme/a9cb1cd82332b23a47e3.woff2
jupyterlab_ariakedark_theme-0.2.3.data/data/share/jupyter/labextensions/jupyterlab_ariakedark_theme/themes/jupyterlab_ariakedark_theme/c503cc5ec5f8b2c7666b.woff2
jupyterlab_ariakedark_theme-0.2.3.data/data/share/jupyter/labextensions/jupyterlab_ariakedark_theme/themes/jupyterlab_ariakedark_theme/index.css
jupyterlab_ariakedark_theme-0.2.3.data/data/share/jupyter/labextensions/jupyterlab_ariakedark_theme/themes/jupyterlab_ariakedark_theme/index.js
jupyterlab_ariakedark_theme-0.2.3.dist-info/METADATA
jupyterlab_ariakedark_theme-0.2.3.dist-info/WHEEL
jupyterlab_ariakedark_theme-0.2.3.dist-info/licenses/LICENSE
jupyterlab_ariakedark_theme-0.2.3.dist-info/RECORD
